ramanujantools/__init__.py
ramanujantools/generic_polynomial.py
ramanujantools/generic_polynomial_test.py
ramanujantools/limit.py
ramanujantools/limit_test.py
ramanujantools/linear_recurrence.py
ramanujantools/linear_recurrence_test.py
ramanujantools/matrix.py
ramanujantools/matrix_benchmark.py
ramanujantools/matrix_test.py
ramanujantools/position.py
ramanujantools/position_test.py
ramanujantools/simplify_object.py
ramanujantools/cmf/__init__.py
ramanujantools/cmf/cmf.py
ramanujantools/cmf/cmf_benchmark.py
ramanujantools/cmf/cmf_test.py
ramanujantools/cmf/d_finite.py
ramanujantools/cmf/ffbar.py
ramanujantools/cmf/ffbar_test.py
ramanujantools/cmf/known_cmfs.py
ramanujantools/cmf/known_cmfs_test.py
ramanujantools/cmf/meijer_g.py
ramanujantools/cmf/meijer_g_test.py
ramanujantools/cmf/pfq.py
ramanujantools/cmf/pfq_test.py
ramanujantools/flint_core/__init__.py
ramanujantools/flint_core/context.py
ramanujantools/flint_core/numeric_matrix.py
ramanujantools/flint_core/numeric_matrix_test.py
ramanujantools/flint_core/rational.py
ramanujantools/flint_core/rational_test.py
ramanujantools/flint_core/symbolic_matrix.py
ramanujantools/flint_core/symbolic_matrix_test.py
ramanujantools/pcf/__init__.py
ramanujantools/pcf/hypergeometric.py
ramanujantools/pcf/hypergeometric_test.py
ramanujantools/pcf/pcf.py
ramanujantools/pcf/pcf_test.py
ramanujantools/solvers/README.md
ramanujantools/solvers/__init__.py
ramanujantools/solvers/coboundary_solver.py
ramanujantools/solvers/coboundary_solver_test.py
ramanujantools/solvers/euler_solver.py
ramanujantools/solvers/euler_solver_test.py
ramanujantools/solvers/ffbar_solver.py
ramanujantools/solvers/ffbar_solver_test.py
ramanujantools/utils/__init__.py
ramanujantools/utils/batched.py
ramanujantools/utils/batched_test.py
ramanujantools-0.0.5.dist-info/METADATA
ramanujantools-0.0.5.dist-info/WHEEL
ramanujantools-0.0.5.dist-info/licenses/LICENSE
ramanujantools-0.0.5.dist-info/RECORD
