Metadata-Version: 2.4
Name: ramanujantools
Version: 0.0.5
Summary: Official symbolic and numeric research tools developed by the Ramanujan Machine team
Project-URL: Homepage, https://www.ramanujanmachine.com/
Project-URL: Repository, https://github.com/RamanujanMachine/ramanujantools
Author-email: Ramanujan Machine Group <ramanujan.machine@gmail.com>
License: MIT License
License-File: LICENSE
Requires-Python: >=3.11
Requires-Dist: gmpy2>=2.2.0
Requires-Dist: mpmath>=1.3.0
Requires-Dist: numpy>=2.0.0
Requires-Dist: python-flint>=0.7.0
Requires-Dist: sympy>=1.11.0
Requires-Dist: tqdm>=4.65.0
Provides-Extra: dev
Requires-Dist: pytest>=8.2.0; extra == 'dev'
